dimmerpatch/__init__.py
dimmerpatch/dimmerpatch.py
dimmerpatch-0.1.6.dist-info/LICENSE
dimmerpatch-0.1.6.dist-info/METADATA
dimmerpatch-0.1.6.dist-info/WHEEL
dimmerpatch-0.1.6.dist-info/top_level.txt
dimmerpatch-0.1.6.dist-info/RECORD
