Metadata-Version: 2.1
Name: dimmerpatch
Version: 0.1.6
Summary: Configure patch panels of light and dimmer fixtures
Home-page: https://github.com/jondlove/dimmerpatch
Author: Jonathan Love
Author-email: jon.d.love@gmail.com
License: UNKNOWN
Project-URL: Bug Tracker, https://github.com/jondlove/dimmerpatch/issues
Platform: UNKNOWN
Classifier: Programming Language :: Python :: 3
Classifier: License :: OSI Approved :: MIT License
Classifier: Operating System :: OS Independent
Requires-Python: >=3.6
License-File: LICENSE
